README.rst
setup.py
django_rest_framework_timedeltafield.egg-info/PKG-INFO
django_rest_framework_timedeltafield.egg-info/SOURCES.txt
django_rest_framework_timedeltafield.egg-info/dependency_links.txt
django_rest_framework_timedeltafield.egg-info/top_level.txt
timedelta_drf/__init__.py
timedelta_drf/serializers.py