Metadata-Version: 1.0
Name: django-rest-framework-timedeltafield
Version: 0.0.2
Summary: Django Rest Framework serializer field for timedelta fields.
Home-page: https://github.com/RyanPineo/django-rest-framework-timedelta-field
Author: Ryan Pineo
Author-email: ryanpineo@gmail.com
License: UNKNOWN
Platform: UNKNOWN
